README.rst
setup.py
PyTEA.egg-info/PKG-INFO
PyTEA.egg-info/SOURCES.txt
PyTEA.egg-info/dependency_links.txt
PyTEA.egg-info/top_level.txt
pytea/__init__.py
pytea/compat.py