Metadata-Version: 1.0
Name: PyTEA
Version: 0.1.0
Summary: Tiny Encryption Algorithm (TEA) in Python.
Home-page: https://github.com/codeif/PyTEA
Author: codeif
Author-email: me@codeif.com
License: MIT
Platform: UNKNOWN
